dj_aidocgen/__init__.py
dj_aidocgen/cli.py
dj_aidocgen-0.1.1.dist-info/licenses/LICENSE
dj_aidocgen-0.1.1.dist-info/METADATA
dj_aidocgen-0.1.1.dist-info/WHEEL
dj_aidocgen-0.1.1.dist-info/entry_points.txt
dj_aidocgen-0.1.1.dist-info/top_level.txt
dj_aidocgen-0.1.1.dist-info/RECORD
