Metadata-Version: 2.4
Name: dj-aidocgen
Version: 0.1.1
Summary: CLI генератор документации для Django endpoints: Markdown + Structurizr PNG или Mermaid
Author: bda82
License: MIT
Project-URL: Homepage, https://github.com/bda82/dj-aidocgen
Project-URL: Repository, https://github.com/bda82/dj-aidocgen
Requires-Python: >=3.9
License-File: LICENSE
Requires-Dist: django>=3.2
Requires-Dist: openai>=1.30.0
Dynamic: license-file
